smi_python_tbi_runner/__init__.py
smi_python_tbi_runner/project.py
smi_python_tbi_runner/tbi_runner.py
smi_python_tbi_runner/runners/__init__.py
smi_python_tbi_runner/runners/tbi-runner.py
test/__init__.py
test/it_example.py
test/test_example.py
smi_python_tbi_runner-1.0.0.dist-info/LICENSE
smi_python_tbi_runner-1.0.0.dist-info/METADATA
smi_python_tbi_runner-1.0.0.dist-info/WHEEL
smi_python_tbi_runner-1.0.0.dist-info/top_level.txt
smi_python_tbi_runner-1.0.0.dist-info/RECORD
