Metadata-Version: 2.1
Name: smi-python-tbi-runner
Version: 1.0.0
Summary: setmy.info Python TBI runner library.
Home-page: https://github.com/setmy-info/python-tbi-runner
Author: Imre Tabur
Author-email: info@setmy.info
License: MIT
License-File: LICENSE
Requires-Dist: smi-python-commons ==0.3.3
Requires-Dist: smi-python-runner ==1.3.0
